<?xml version="1.0" encoding="UTF-8" standalone="no"?>
<description>
<key description="Chave interativa para gêneros de angiospermas aquáticas e palustres do Recôncavo da Bahia" title="Angiospermas Aquáticas e Palustres do Recôncavo da Bahia"/>
<entity name="Peltaea (MALV)">
<media>
<media_item label="no caption" type="image">
<source path="../Images/Malvaceae Peltaea obsita (Colla) Krapov. &amp; Cristóbal Santo Amaro flo.JPG" type="image/jpeg"/>
<icon path="../Thumbs/Malvaceae Peltaea obsita (Colla) Krapov. &amp; Cristóbal Santo Amaro flo_TN.jpg" type="image/jpeg"/>
</media_item>
<media_item label="no caption" type="image">
<source path="../Images/Malvaceae Peltaea obsita (Colla) Krapov. &amp; Cristóbal Santo Amaro.JPG" type="image/jpeg"/>
<icon path="../Thumbs/Malvaceae Peltaea obsita (Colla) Krapov. &amp; Cristóbal Santo Amaro_TN.jpg" type="image/jpeg"/>
</media_item>
</media>
</entity>
</description>
